geeml/__init__.py
geeml/extract.py
geeml/geeml.py
geeml/inference.py
geeml/utils.py
geeml-0.0.7.dist-info/LICENSE
geeml-0.0.7.dist-info/METADATA
geeml-0.0.7.dist-info/WHEEL
geeml-0.0.7.dist-info/dependency_links.txt
geeml-0.0.7.dist-info/top_level.txt
geeml-0.0.7.dist-info/RECORD
