Metadata-Version: 2.1
Name: geeml
Version: 0.0.7
Summary: A python package to extract gee data for machine learning.
Home-page: https://github.com/Geethen/geeml
Author: Geethen Singh
Author-email: geethen.singh@gmail.com
License: MIT license
Keywords: geeml
Classifier: Development Status :: 2 - Pre-Alpha
Classifier: Intended Audience :: Developers
Classifier: License :: OSI Approved :: MIT License
Classifier: Natural Language :: English
Classifier: Programming Language :: Python :: 3
Classifier: Programming Language :: Python :: 3.7
Classifier: Programming Language :: Python :: 3.8
Classifier: Programming Language :: Python :: 3.9
Requires-Python: >=3.7
License-File: LICENSE
Requires-Dist: earthengine-api
